<?xml version="1.0" encoding="utf-8" ?>

<Defs>
	<!-- Klickmala Race (Humanoid Insect Alien Race). 1861316304. https://steamcommunity.com/sharedfiles/filedetails/?id=1861316304 -->
	<rjw.RaceGroupDef>
		<defName>Klickmala_Insect_People</defName>
		
		<raceNames>
			<li>KlickmalaRace</li>
		</raceNames>
		
		<pawnKindNames>
		</pawnKindNames>
		
		<anuses>
			<li>InsectAnus</li>
		</anuses>
		
		<chanceanuses></chanceanuses>

		<femaleBreasts>
			<li>FeaturelessChest</li>
		</femaleBreasts>
		
		<chancefemaleBreasts></chancefemaleBreasts>
		
		<femaleGenitals>
			<li>OvipositorF</li>
		</femaleGenitals>
		
		<chancefemaleGenitals></chancefemaleGenitals>

		<maleBreasts>
			<li>FeaturelessChest</li>
		</maleBreasts>
		
		<chancemaleBreasts></chancemaleBreasts>

		<maleGenitals>
			<li>OvipositorM</li>
		</maleGenitals>
		
		<chancemaleGenitals></chancemaleGenitals>
		
		<tags>
			<li>Chitin</li>
		</tags>

		<!-- All the values below are the defaults and can be omitted. -->
		<hasSingleGender>false</hasSingleGender>
		<hasSexNeed>true</hasSexNeed>
		<hasFertility>true</hasFertility>
		<hasPregnancy>true</hasPregnancy>
		<oviPregnancy>true</oviPregnancy>
		<ImplantEggs>true</ImplantEggs>

	</rjw.RaceGroupDef>
</Defs>