<?xml version="1.0" encoding="utf-8" ?>

<Defs>
	
	<!-- Oni of the Rim. 1632244750. https://steamcommunity.com/sharedfiles/filedetails/?id=1632244750 -->
	<rjw.RaceGroupDef>
		
		<defName>Oni</defName>
		
		<raceNames>
			<li>AOni</li>
			<li>Alien_AncestralAOni</li>
		</raceNames>
		
		<pawnKindNames>
		</pawnKindNames>
		
		<anuses>
			<li>DemonAnus</li>
		</anuses>
		
		<chanceanuses></chanceanuses>

		<femaleBreasts>
			<li>Breasts</li>
		</femaleBreasts>
		
		<chancefemaleBreasts></chancefemaleBreasts>
		
		<femaleGenitals>
			<li>DemonVagina</li>
		</femaleGenitals>
		
		<chancefemaleGenitals></chancefemaleGenitals>

		<maleBreasts>
			<li>Breasts</li>
		</maleBreasts>
		
		<chancemaleBreasts></chancemaleBreasts>

		<maleGenitals>
			<li>DemonPenis</li>
		</maleGenitals>
		
		<chancemaleGenitals></chancemaleGenitals>
		
		<tags>
			<li>Demon</li>
			<li>Feathers</li>
		</tags>

		<hasSingleGender>false</hasSingleGender>
		<hasSexNeed>true</hasSexNeed>
		<hasFertility>true</hasFertility>
		<hasPregnancy>true</hasPregnancy>
		<oviPregnancy>false</oviPregnancy>
		<ImplantEggs>false</ImplantEggs>

	</rjw.RaceGroupDef>
	
	<rjw.RaceGroupDef>
		
		<defName>Oni_Animal</defName>
		
		<raceNames>
			<li>Ornimegalonyx</li>
		</raceNames>
		
		<pawnKindNames>
		</pawnKindNames>
		
		<anuses>
			<li>CloacalAnus</li>
		</anuses>
		
		<chanceanuses></chanceanuses>

		<femaleBreasts>
			<li>FeaturelessChest</li>
		</femaleBreasts>
		
		<chancefemaleBreasts></chancefemaleBreasts>
		
		<femaleGenitals>
			<li>CloacalVagina</li>
		</femaleGenitals>
		
		<chancefemaleGenitals></chancefemaleGenitals>

		<maleBreasts>
			<li>FeaturelessChest</li>
		</maleBreasts>
		
		<chancemaleBreasts></chancemaleBreasts>

		<maleGenitals>
			<li>CloacalPenis</li>
		</maleGenitals>
		
		<chancemaleGenitals></chancemaleGenitals>
		
		<tags>
			<li>Feathers</li>
		</tags>

		<hasSingleGender>false</hasSingleGender>
		<hasSexNeed>true</hasSexNeed>
		<hasFertility>true</hasFertility>
		<hasPregnancy>true</hasPregnancy>
		<oviPregnancy>false</oviPregnancy>
		<ImplantEggs>false</ImplantEggs>

	</rjw.RaceGroupDef>
</Defs>